eggdriver/__init__.py
eggdriver/__main__.py
eggdriver/app.py
eggdriver/driver.py
eggdriver/pypi.py
eggdriver/version.py
eggdriver/library/__init__.py
eggdriver/library/commands.py
eggdriver/library/repos.py
eggdriver/news/__init__.py
eggdriver/news/app.py
eggdriver/news/config.py
eggdriver/news/news.py
eggdriver/nqs/__init__.py
eggdriver/nqs/core/__init__.py
eggdriver/nqs/core/core.py
eggdriver/nqs/core/functions.py
eggdriver/nqs/core/kernel.py
eggdriver/nqs/core/quantum.py
eggdriver/nqs/core/reader.py
eggdriver/nqs/developer/__init__.py
eggdriver/nqs/developer/app.py
eggdriver/nqs/developer/run.py
eggdriver/nqs/developer/write.py
eggdriver/resources/__init__.py
eggdriver/resources/auth.py
eggdriver/resources/constants.py
eggdriver/resources/extensions.py
eggdriver/resources/help.py
eggdriver/resources/modules.py
eggdriver/resources/parser.py
eggdriver/resources/strings.py
eggdriver/resources/utils.py
eggdriver/resources/web.py
eggdriver/resources/algorithms/__init__.py
eggdriver/resources/algorithms/solver/__init__.py
eggdriver/resources/algorithms/solver/bijection.py
eggdriver/resources/algorithms/solver/dichotomy.py
eggdriver/resources/console/__init__.py
eggdriver/resources/console/display.py
eggdriver/resources/console/progress.py
eggdriver/resources/math/__init__.py
eggdriver/resources/math/constants.py
eggdriver/resources/math/float.py
eggdriver/resources/math/functions.py
eggdriver/resources/math/linear.py
eggdriver/resources/math/polynomial.py
eggdriver/resources/math/algorithms/__init__.py
eggdriver/resources/math/algorithms/limit.py
eggdriver/resources/math/algorithms/solver/__init__.py
eggdriver/resources/math/algorithms/solver/dichotomy.py
eggdriver/resources/math/calculus/__init__.py
eggdriver/resources/math/calculus/derivatives.py
eggdriver/resources/math/calculus/limit.py
eggdriver/resources/math/calculus/series.py
eggdriver/resources/math/linear/__init__.py
eggdriver/resources/math/linear/utils.py
eggdriver/resources/math/theoric/__init__.py
eggdriver-0.0.1.dist-info/LICENSE
eggdriver-0.0.1.dist-info/METADATA
eggdriver-0.0.1.dist-info/WHEEL
eggdriver-0.0.1.dist-info/top_level.txt
eggdriver-0.0.1.dist-info/RECORD
