Metadata-Version: 2.1
Name: eggdriver
Version: 0.0.1
Summary: Your proyect trusted driver.
Home-page: https://github.com/PythonForChange/eggdriver
Author: Emmanuel Norambuena
Author-email: eanorambuena@uc.cl
License: MIT
Project-URL: Bug Reports, https://github.com/PythonForChange/eggdriver/issues
Project-URL: Source, https://github.com/PythonForChange/eggdriver
Keywords: kit,quantum,development
Platform: UNKNOWN
Classifier: Development Status :: 5 - Production/Stable
Classifier: Intended Audience :: Developers
Classifier: Topic :: Software Development :: Build Tools
Classifier: License :: OSI Approved :: MIT License
Classifier: Programming Language :: Python :: 3
Classifier: Programming Language :: Python :: 3.6
Classifier: Programming Language :: Python :: 3.7
Classifier: Programming Language :: Python :: 3.8
Classifier: Programming Language :: Python :: 3.9
Classifier: Programming Language :: Python :: 3 :: Only
Requires-Python: >=3.6, <4
License-File: LICENSE
Requires-Dist: numpy
Requires-Dist: tensorflow
Requires-Dist: keras
Requires-Dist: Colr
Requires-Dist: opencv-contrib-python
Requires-Dist: mediapipe
Requires-Dist: pipwin
